{
	"pages": [ //pages数组中第一项表示应用启动页，参考：https://uniapp.dcloud.io/collocation/pages
		{
			"path": "pages/index/index",
			"style": {
				"navigationBarTitleText": "首页"
			}
		}, {
			"path": "pages/news/news",
			"style": {
				"navigationBarTitleText": "新闻",
				"navigationBarBackgroundColor": "#272822",
				"navigationBarTextStyle": "white"
			}
		}, {
			"path": "pages/demo/demo",
			"style": {
				"navigationBarTitleText": "Demo",
				"enablePullDownRefresh": true
			}

		}, {
			"path": "pages/demo/swiper/swiper",
			"style": {
				"navigationBarTitleText": "swiper"
			}

		}, {
			"path": "pages/demo/scroll-view/scroll-view",
			"style": {
				"navigationBarTitleText": "scroll-view"
			}

		}, {
			"path": "pages/demo/nav/nav",
			"style": {
				"navigationBarTitleText": "nav"
			}
		}, {
			"path": "pages/demo/components/components",
			"style": {
				"navigationBarTitleText": "components"
			}
		}, {
			"path": "pages/demo/route/route",
			"style": {
				"navigationBarTitleText": "route"
			}
		}, {
			"path": "pages/demo/route/route2",
			"style": {
				"navigationBarTitleText": "route2"
			}
		}
	],
	"globalStyle": {
		"navigationBarBackgroundColor": "#F8F8F8",
		"navigationBarTextStyle": "black",
		"navigationBarTitleText": "uni-app",
		"backgroundColor": "#F8F8F8"
	},
	"uniIdRouter": {},
	"tabBar": {
		"color": "#333",
		"selectedColor": "#015FF9",
		"list": [{
			"text": "首页",
			"pagePath": "pages/index/index"
		}, {
			"text": "新闻",
			"pagePath": "pages/news/news"
		}, {
			"text": "Demo",
			"pagePath": "pages/demo/demo"
		}]
	}
}